instruction_decoder.v
// instr_mem.v - instruction memory

module instruction_decoder (
    input clk,
    input       [15:0] instruction_address,
    output      [15:0] instruction
);

// array of 64 32-bit words or instructions
reg [15:0] instruction_ram [0:255];

initial begin
    $readmemb("lc3_test.hex", instruction_ram);
end

// word-aligned memory access
// combinational read logic
assign instruction = instruction_ram[instruction_address];

endmodule

ram.v
// ram.v
// memory

// What all should RAM do:
// take in ptr, gives you value at that ram location or ptr to ptr
// writeenable and input word both must exist also

module ram (
    input wire clk,
    input wire reset,

    input wire WrEn,
    input wire PtrToPtr, //if 1 then ptr to ptr

    input wire [15:0] address,
    input wire [15:0] word_in,

    output wire [15:0] word_out
);
    reg [15:0] memory [0:65535];
    wire [15:0] indirect_address;
    wire [15:0] effective_address;
    assign indirect_address = memory[address];
    assign effective_address = (PtrToPtr) ? indirect_address : address;

    // Debug wires (for waveform visibility only)
  wire [15:0] M0 = memory[0];
  wire [15:0] M1 = memory[1];
  wire [15:0] M2 = memory[2];
  wire [15:0] M3 = memory[3];
  wire [15:0] M4 = memory[4];
  wire [15:0] M5 = memory[5];
  wire [15:0] M6 = memory[6];
  wire [15:0] M7 = memory[7];
  wire [15:0] M8 = memory[8];
  wire [15:0] M9 = memory[9];
  wire [15:0] M10 = memory[10];
  wire [15:0] M11 = memory[11];
  wire [15:0] M12 = memory[12];
  wire [15:0] M13 = memory[13];
  wire [15:0] M57 = memory[57];
  wire [15:0] M67 = memory[67];

    always @(negedge clk) begin
        if(WrEn) begin
            memory[effective_address] <= word_in;
        end
    end

    assign word_out = memory[effective_address];
endmodule

ALU.v
// ALU module
// part of datapath

module ALU (
    input wire [15:0] data1, data2,

    //control input
    input wire [1:0] ALUControl,

    output wire [15:0] result
);
    //ALUcontrol: 00: Add
    //            01: AND
    //            10: NOT (on data1)

    assign result = (ALUControl == 2'b00) ? (data1 + data2) :
                    (ALUControl == 2'b01) ? (data1 & data2) :
                    (ALUControl == 2'b10) ? (~data1)        :
                                            16'b0;
    
endmodule

ImmExt.v
// ImmExt module
// part of datapath module

module ImmExt (
    input wire [10:0] data,
    input wire [1:0] ExtByHowMuch,
    output wire [15:0] result
);
    // ExtByHowMuch: 00: 5 to 16
    //               01: 6 to 16
    //               10: 9 to 16
    //               11: 11 to 16

    assign result =
        (ExtByHowMuch == 2'b00) ? {{11{data[4]}}, data[4:0]} :
        (ExtByHowMuch == 2'b01) ? {{10{data[5]}}, data[5:0]} :
        (ExtByHowMuch == 2'b10) ? {{7{data[8]}}, data[8:0]} :
        (ExtByHowMuch == 2'b11) ? {{5{data[10]}}, data[10:0]} : 16'd0;
endmodule

register_handler.v
module register_handler (
    input wire [2:0] SR1, SR2, DR,
    input wire [15:0] data,
    input wire [15:0] incremented_PC,
    input wire RegWrite,
    input wire clk,
    input wire reset,

    output wire [15:0] data_SR1, data_SR2,
    output wire BrFinalBoss
);

    reg [15:0] regfile [0:7];
    reg N, Zee, P;

                                    // Debug wires (for waveform visibility only)
                                  wire [15:0] R0 = regfile[0];
                                  wire [15:0] R1 = regfile[1];
                                  wire [15:0] R2 = regfile[2];
                                  wire [15:0] R3 = regfile[3];
                                  wire [15:0] R4 = regfile[4];
                                  wire [15:0] R5 = regfile[5];
                                  wire [15:0] R6 = regfile[6];
                                  wire [15:0] R7 = regfile[7];

    // Asynchronous read
    assign data_SR1 = regfile[SR1];
    assign data_SR2 = regfile[SR2];

    // Single sequential block
    always @(negedge clk) begin
        if (reset) begin
            regfile[0] <= 16'd0;
            regfile[1] <= 16'd0;
            regfile[2] <= 16'd0;
            regfile[3] <= 16'd0;
            regfile[4] <= 16'd0;
            regfile[5] <= 16'd0;
            regfile[6] <= 16'd0;
            regfile[7] <= 16'd0;

            N   <= 1'b0;
            Zee <= 1'b0;
            P   <= 1'b0;
        end
        else if (RegWrite) begin
            if (DR == 3'b111)
                regfile[7] <= incremented_PC;
            else
                regfile[DR] <= data;

            // Condition codes update
            N   <= data[15];
            Zee <= (data == 16'd0);
            P   <= (~data[15]) & (data != 16'd0);
        end
    end

    assign BrFinalBoss =
            (DR[0] & P) |
            (DR[1] & Zee) |
            (DR[2] & N);

endmodule

datapath.v
// datapath modules

module datapath (
    input wire clk,
    input wire reset,
    // instruction
    input wire [15:0] instruction,
    //input wire from ram's output
    input wire [15:0] rams_output,

    //control inputs
    input wire [1:0] ALUControl, ExtByHowMuch,
    input wire RegWrite, PtrToPtr, SR2Mux, DRMux, RegWriteMux, SRPCMux, BrMux, ImmSR2Mux, JMPMux,

    //outputs to RAM
    output wire [15:0] ram_address, input_word_to_ram,

    //output to instruction
    output wire [15:0] PC
);
    // wire declarations
    wire [2:0] SR1, SR2, DR;
    wire [15:0] register_data, data_SR1, data_SR2;
    wire BrFinalBoss;

    wire [15:0] ImmExtResult, ImmExtALUinput2Intermediate;

    wire [15:0] ALUinput1, ALUinput2, ALUoutput;

    wire [15:0] incremented_PC_wire, PC_internal;

    //hardware declarations
    register_handler register_handler(
        .SR1(SR1),
        .SR2(SR2),
        .DR(DR),
        .data(register_data),
        .incremented_PC(incremented_PC_wire),
        .RegWrite(RegWrite),
        .clk(clk),
        .reset(reset),
        .data_SR1(data_SR1),
        .data_SR2(data_SR2),
        .BrFinalBoss(BrFinalBoss)
    );

    ImmExt ImmExt(
        .data(instruction[10:0]),
        .ExtByHowMuch(ExtByHowMuch),
        .result(ImmExtResult)
    );

    ALU ALU(
        .data1(ALUinput1),
        .data2(ALUinput2),
        .ALUControl(ALUControl),
        .result(ALUoutput)
    );
    
    //combinational wire logic
    assign SR1 = instruction[8:6];
    assign SR2 = (SR2Mux) ? instruction[11:9] : instruction[2:0];
    assign DR = (DRMux) ? 3'd7 : instruction[11:9];
    assign register_data = (RegWriteMux) ? rams_output : ALUoutput;
    assign ImmExtALUinput2Intermediate = (BrFinalBoss) ? ImmExtResult : 16'd0;

    assign ALUinput1 = (SRPCMux) ? data_SR1 : incremented_PC_wire;
    assign ALUinput2 = (ImmSR2Mux) ? data_SR2 : (BrMux) ? ImmExtALUinput2Intermediate : ImmExtResult;

    assign ram_address = ALUoutput;
    assign input_word_to_ram = data_SR2;

    //PC logic
    assign PC_internal = (reset) ? 16'd0 : (JMPMux) ? ALUoutput : incremented_PC_wire;
    assign incremented_PC_wire = PC + 16'd1;
    reg [15:0] PC_reg, intermediate_PC_reg;
    initial begin
        PC_reg <= 16'd0;
        intermediate_PC_reg <= 16'd0;
    end
    always @(posedge clk) begin
        if (!reset) begin
           PC_reg <= intermediate_PC_reg; 
        end  
    end
    always @(negedge clk) begin
        if (!reset) begin
           intermediate_PC_reg <= PC_internal; 
        end
    end
    assign PC = PC_reg;

endmodule

controller.v
// controller module
// under cpu

module controller (
    input wire [15:0] instruction,
    input wire clk,
    input wire reset,

    output reg  [1:0] ALUControl,
    output reg  [1:0] ExtByHowMuch,
    output wire RegWrite,
    output wire PtrToPtr,
    output wire WriteEnable,
    output wire SR2Mux,
    output wire DRMux,
    output wire RegWriteMux,
    output wire SRPCMux,
    output wire BrMux,
    output wire ImmSR2Mux,
    output wire JMPMux
);

    wire [3:0] opcode;
    assign opcode = instruction[15:12];

    // ALU Control
    always @(*) begin
        case (opcode)
            4'b0101: ALUControl = 2'b01; // AND
            4'b1001: ALUControl = 2'b10; // NOT
            default: ALUControl = 2'b00; // ADD
        endcase
    end

    // Immediate extension size
    always @(*) begin
        casez (opcode)
            4'b0100: ExtByHowMuch = 2'b11; // 11 to 16
            4'b??01: ExtByHowMuch = 2'b00; // 5 to 16
            4'b011?: ExtByHowMuch = 2'b01; // 6 to 16
            4'b1100: ExtByHowMuch = 2'b01; // 6 to 16
            default: ExtByHowMuch = 2'b10; // 9 to 16
        endcase
    end

    // RegWrite
    assign RegWrite = (opcode[0] ^ opcode[1] ^ opcode[2]);

    // RAM controls
    assign PtrToPtr   = opcode[3];
    assign WriteEnable = ~(opcode[3] & opcode[2]) & (opcode[1] & opcode[0]);

    // SR2Mux
    assign SR2Mux = ~opcode[2] & opcode[0];

    // DRMux
    assign DRMux = ~opcode[3] & opcode[2] & ~opcode[1] & ~opcode[0];

    // RegWriteMux
    assign RegWriteMux = ~(opcode[3] & opcode[2]) & (opcode[1] & ~opcode[0]);

    // SRPCMux
    assign SRPCMux = ((~opcode[1] & opcode[0]) & (~opcode[3] | ~opcode[2])) |
                     ((~opcode[3] & opcode[2] & opcode[1])) | (opcode[3] & opcode[2] & ~opcode[1]) |
                     (opcode[2] & ~opcode[1] & ~opcode[0] & ~(opcode[3] | instruction[11]));//help

    // Branch Mux
    assign BrMux = ~opcode[3] & ~opcode[2] & ~opcode[1] & ~opcode[0];

    // Immediate vs SR2 Mux
    assign ImmSR2Mux = (opcode[0] & ~opcode[1] & ~instruction[5]);

    // JMP Mux
    assign JMPMux = reset ? 1'b0 :
                (~opcode[0] & ~opcode[1]);

endmodule

cpu.v
// cpu module
// origin: lc3computer
// includes the following modules:
//		datapath
//		control

module cpu (
    //input from instruction_decoder
    input wire [15:0] instruction,

    //input from RAM
	input wire [15:0] memory_data,
	 
	//misc inputs
    input wire clk,
    input wire reset,
	 
	//outputs for instruction_decoder
    output wire [15:0] PC,
	 
	//outputs for RAM
    output wire [15:0] ram_address,
    output wire [15:0] input_word_to_ram,
    
	//control outputs for RAM
    output wire PtrToPtr,
    output wire WriteEnable
);

    wire [1:0] ALUControl, ExtByHowMuch;
    wire RegWrite, SR2Mux, DRMux, RegWriteMux, SRPCMux, BrMux, ImmSR2Mux, JMPMux;

    controller controller(
        .instruction(instruction),
        .clk(clk),
        .reset(reset),
        .ALUControl(ALUControl),
        .ExtByHowMuch(ExtByHowMuch),
        .RegWrite(RegWrite),
        .PtrToPtr(PtrToPtr),
        .WriteEnable(WriteEnable),
        .SR2Mux(SR2Mux),
        .DRMux(DRMux),
        .RegWriteMux(RegWriteMux),
        .SRPCMux(SRPCMux),
        .BrMux(BrMux),
        .ImmSR2Mux(ImmSR2Mux),
        .JMPMux(JMPMux)
    );

    datapath datapath(
        .clk(clk),
        .reset(reset),
        .instruction(instruction),
        .rams_output(memory_data),
        .ALUControl(ALUControl),
        .ExtByHowMuch(ExtByHowMuch),
        .RegWrite(RegWrite),
        .PtrToPtr(PtrToPtr),
        .SR2Mux(SR2Mux),
        .DRMux(DRMux),
        .RegWriteMux(RegWriteMux),
        .SRPCMux(SRPCMux),
        .BrMux(BrMux),
        .ImmSR2Mux(ImmSR2Mux),
        .JMPMux(JMPMux),
        .ram_address(ram_address),
        .input_word_to_ram(input_word_to_ram),
        .PC(PC)
    );
endmodule

lc3computer.v
// lc3computer.v
// Top level entry
// immediate inclusive modules are:
//		instruction decoder
//		CPU
//		RAM equivalent

module lc3computer (
    input wire clk,
    input wire reset
);
    wire [15:0] instruction, memory_data, ram_address, input_word_to_ram, PC;
    wire PtrToPtr, WriteEnable;

    cpu cpu1(
        .instruction(instruction),
        .memory_data(memory_data),
        .clk(clk),
        .reset(reset),
        .PC(PC),
        .ram_address(ram_address),
        .input_word_to_ram(input_word_to_ram),
        .PtrToPtr(PtrToPtr),
        .WriteEnable(WriteEnable)
    );

    ram ram1(
        .clk(clk),
        .reset(reset),
        .WrEn(WriteEnable),
        .PtrToPtr(PtrToPtr),
        .address(ram_address),
        .word_in(input_word_to_ram),
        .word_out(memory_data)
    );

    instruction_decoder instruction_decoder(
        .clk(clk),
        .instruction_address(PC),
        .instruction(instruction)
    );
endmodule

tb.v
`timescale 1ns/1ps

module tb;

    reg clk;
    reg reset;

    // DUT
    lc3computer dut (
        .clk(clk),
        .reset(reset)
    );

    // ================================
    // CLOCK: 100 MHz
    // ================================
    initial begin
        clk = 0;
        forever #5 clk = ~clk;
    end

    // ================================
    // RESET SEQUENCE
    // ================================
    initial begin
        reset = 1;      // assert reset
        #17;            // hold for 2 clock cycles
        reset = 0;      // release reset
    end

    // ================================
    // WAVE DUMP
    // ================================
    initial begin
        $dumpfile("lc3_full_debug.vcd");
        $dumpvars(0, tb);
    end

    // ================================
    // MONITOR DISPLAY
    // ================================
    always @(posedge clk) begin
        $display("------------------------------------------------------------");
        $display("Time = %0t | Reset = %b", $time, reset);

        $display("PC = %h | Instruction = %h",
                 dut.cpu1.PC,
                 dut.instruction);

        $display("SR1_data = %h | SR2_data = %h",
                 dut.cpu1.datapath.data_SR1,
                 dut.cpu1.datapath.data_SR2);

        $display("ALU_in1 = %h | ALU_in2 = %h | ALU_out = %h",
                 dut.cpu1.datapath.ALUinput1,
                 dut.cpu1.datapath.ALUinput2,
                 dut.cpu1.datapath.ALUoutput);

        $display("RAM_addr = %h | RAM_in = %h | RAM_out = %h | WE = %b | PtrToPtr = %b",
                 dut.ram_address,
                 dut.input_word_to_ram,
                 dut.memory_data,
                 dut.WriteEnable,
                 dut.PtrToPtr);

        $display("ALUControl=%b Ext=%b RegWrite=%b",
                 dut.cpu1.ALUControl,
                 dut.cpu1.ExtByHowMuch,
                 dut.cpu1.RegWrite);

        $display("SR2Mux=%b DRMux=%b RegWriteMux=%b SRPCMux=%b BrMux=%b ImmSR2Mux=%b JMPMux=%b",
                 dut.cpu1.SR2Mux,
                 dut.cpu1.DRMux,
                 dut.cpu1.RegWriteMux,
                 dut.cpu1.SRPCMux,
                 dut.cpu1.BrMux,
                 dut.cpu1.ImmSR2Mux,
                 dut.cpu1.JMPMux);
    end

    // ================================
    // SIMULATION CONTROL
    // ================================
    initial begin
        $display("Starting LC3 Debug Simulation...");
        #1000;
        $display("Simulation Finished.");
        $finish;
    end

endmodule

lc3_full_debug.vcd
$date
	Tue Mar 10 18:48:16 2026
$end
$version
	Icarus Verilog
$end
$timescale
	1ps
$end
$scope module tb $end
$var reg 1 ! clk $end
$var reg 1 " reset $end
$scope module dut $end
$var wire 1 ! clk $end
$var wire 1 " reset $end
$var wire 16 # ram_address [15:0] $end
$var wire 16 $ memory_data [15:0] $end
$var wire 16 % instruction [15:0] $end
$var wire 16 & input_word_to_ram [15:0] $end
$var wire 1 ' WriteEnable $end
$var wire 1 ( PtrToPtr $end
$var wire 16 ) PC [15:0] $end
$scope module cpu1 $end
$var wire 1 ! clk $end
$var wire 1 " reset $end
$var wire 16 * ram_address [15:0] $end
$var wire 16 + memory_data [15:0] $end
$var wire 16 , instruction [15:0] $end
$var wire 16 - input_word_to_ram [15:0] $end
$var wire 1 ' WriteEnable $end
$var wire 1 . SRPCMux $end
$var wire 1 / SR2Mux $end
$var wire 1 0 RegWriteMux $end
$var wire 1 1 RegWrite $end
$var wire 1 ( PtrToPtr $end
$var wire 16 2 PC [15:0] $end
$var wire 1 3 JMPMux $end
$var wire 1 4 ImmSR2Mux $end
$var wire 2 5 ExtByHowMuch [1:0] $end
$var wire 1 6 DRMux $end
$var wire 1 7 BrMux $end
$var wire 2 8 ALUControl [1:0] $end
$scope module controller $end
$var wire 1 7 BrMux $end
$var wire 1 6 DRMux $end
$var wire 1 4 ImmSR2Mux $end
$var wire 1 1 RegWrite $end
$var wire 1 0 RegWriteMux $end
$var wire 1 / SR2Mux $end
$var wire 1 . SRPCMux $end
$var wire 1 ' WriteEnable $end
$var wire 1 ! clk $end
$var wire 1 " reset $end
$var wire 4 9 opcode [3:0] $end
$var wire 16 : instruction [15:0] $end
$var wire 1 ( PtrToPtr $end
$var wire 1 3 JMPMux $end
$var reg 2 ; ALUControl [1:0] $end
$var reg 2 < ExtByHowMuch [1:0] $end
$upscope $end
$scope module datapath $end
$var wire 2 = ALUControl [1:0] $end
$var wire 1 7 BrMux $end
$var wire 1 6 DRMux $end
$var wire 2 > ExtByHowMuch [1:0] $end
$var wire 1 4 ImmSR2Mux $end
$var wire 1 3 JMPMux $end
$var wire 1 ( PtrToPtr $end
$var wire 1 1 RegWrite $end
$var wire 1 0 RegWriteMux $end
$var wire 1 / SR2Mux $end
$var wire 1 . SRPCMux $end
$var wire 1 ! clk $end
$var wire 16 ? input_word_to_ram [15:0] $end
$var wire 16 @ ram_address [15:0] $end
$var wire 1 " reset $end
$var wire 16 A register_data [15:0] $end
$var wire 16 B rams_output [15:0] $end
$var wire 16 C instruction [15:0] $end
$var wire 16 D incremented_PC_wire [15:0] $end
$var wire 16 E data_SR2 [15:0] $end
$var wire 16 F data_SR1 [15:0] $end
$var wire 3 G SR2 [2:0] $end
$var wire 3 H SR1 [2:0] $end
$var wire 16 I PC_internal [15:0] $end
$var wire 16 J PC [15:0] $end
$var wire 16 K ImmExtResult [15:0] $end
$var wire 16 L ImmExtALUinput2Intermediate [15:0] $end
$var wire 3 M DR [2:0] $end
$var wire 1 N BrFinalBoss $end
$var wire 16 O ALUoutput [15:0] $end
$var wire 16 P ALUinput2 [15:0] $end
$var wire 16 Q ALUinput1 [15:0] $end
$var reg 16 R PC_reg [15:0] $end
$var reg 16 S intermediate_PC_reg [15:0] $end
$scope module ALU $end
$var wire 2 T ALUControl [1:0] $end
$var wire 16 U data1 [15:0] $end
$var wire 16 V data2 [15:0] $end
$var wire 16 W result [15:0] $end
$upscope $end
$scope module ImmExt $end
$var wire 2 X ExtByHowMuch [1:0] $end
$var wire 11 Y data [10:0] $end
$var wire 16 Z result [15:0] $end
$upscope $end
$scope module register_handler $end
$var wire 1 N BrFinalBoss $end
$var wire 3 [ DR [2:0] $end
$var wire 16 \ R0 [15:0] $end
$var wire 16 ] R1 [15:0] $end
$var wire 16 ^ R2 [15:0] $end
$var wire 16 _ R3 [15:0] $end
$var wire 16 ` R4 [15:0] $end
$var wire 16 a R5 [15:0] $end
$var wire 16 b R6 [15:0] $end
$var wire 16 c R7 [15:0] $end
$var wire 1 1 RegWrite $end
$var wire 3 d SR1 [2:0] $end
$var wire 3 e SR2 [2:0] $end
$var wire 1 ! clk $end
$var wire 16 f data [15:0] $end
$var wire 16 g data_SR1 [15:0] $end
$var wire 16 h data_SR2 [15:0] $end
$var wire 16 i incremented_PC [15:0] $end
$var wire 1 " reset $end
$var reg 1 j N $end
$var reg 1 k P $end
$var reg 1 l Zee $end
$upscope $end
$upscope $end
$upscope $end
$scope module instruction_decoder $end
$var wire 1 ! clk $end
$var wire 16 m instruction [15:0] $end
$var wire 16 n instruction_address [15:0] $end
$upscope $end
$scope module ram1 $end
$var wire 16 o M0 [15:0] $end
$var wire 16 p M1 [15:0] $end
$var wire 16 q M10 [15:0] $end
$var wire 16 r M11 [15:0] $end
$var wire 16 s M12 [15:0] $end
$var wire 16 t M13 [15:0] $end
$var wire 16 u M2 [15:0] $end
$var wire 16 v M3 [15:0] $end
$var wire 16 w M4 [15:0] $end
$var wire 16 x M5 [15:0] $end
$var wire 16 y M57 [15:0] $end
$var wire 16 z M6 [15:0] $end
$var wire 16 { M67 [15:0] $end
$var wire 16 | M7 [15:0] $end
$var wire 16 } M8 [15:0] $end
$var wire 16 ~ M9 [15:0] $end
$var wire 1 ( PtrToPtr $end
$var wire 1 ' WrEn $end
$var wire 16 !" address [15:0] $end
$var wire 1 ! clk $end
$var wire 16 "" indirect_address [15:0] $end
$var wire 1 " reset $end
$var wire 16 #" word_in [15:0] $end
$var wire 16 $" word_out [15:0] $end
$var wire 16 %" effective_address [15:0] $end
$upscope $end
$upscope $end
$upscope $end
$enddefinitions $end
$comment Show the parameter values. $end
$dumpall
$end
#0
$dumpvars
b0 %"
bx $"
b0 #"
bx ""
b0 !"
bx ~
bx }
bx |
bx {
bx z
bx y
bx x
bx w
bx v
bx u
bx t
bx s
bx r
bx q
bx p
bx o
b0 n
b1000000100000 m
0l
0k
0j
b1 i
b0 h
b0 g
b0 f
b0 e
b0 d
b0 c
b0 b
b0 a
b0 `
b0 _
b0 ^
b0 ]
b0 \
b0 [
b0 Z
b100000 Y
b0 X
b0 W
b0 V
b0 U
b0 T
b0 S
b0 R
b0 Q
b0 P
b0 O
0N
b0 M
b0 L
b0 K
b0 J
b0 I
b0 H
b0 G
b0 F
b0 E
b1 D
b1000000100000 C
bx B
b0 A
b0 @
b0 ?
b0 >
b0 =
b0 <
b0 ;
b1000000100000 :
b1 9
b0 8
07
06
b0 5
04
03
b0 2
11
00
1/
1.
b0 -
b1000000100000 ,
bx +
b0 *
b0 )
0(
0'
b0 &
b1000000100000 %
bx $
b0 #
1"
0!
$end
#5000
1!
#10000
0!
#15000
1!
#17000
b1 I
0"
#20000
1l
b1 S
0!
#25000
b1010 A
b1010 f
b1010 %"
b1010 #
b1010 *
b1010 @
b1010 !"
b1010 O
b1010 W
b1010 P
b1010 V
b1010 K
b1010 Z
b10 I
b1 M
b1 [
b1 G
b1 e
b1 H
b1 d
b1001101010 Y
b10 D
b10 i
b1001001101010 %
b1001001101010 ,
b1001001101010 :
b1001001101010 C
b1001001101010 m
b1 )
b1 2
b1 J
b1 R
b1 n
1!
#30000
b1010 L
1N
b10100 A
b10100 f
b10100 %"
b10100 #
b10100 *
b10100 @
b10100 !"
b10100 O
b10100 W
b1010 Q
b1010 U
b10 S
1k
0l
b1010 F
b1010 g
b1010 &
b1010 -
b1010 ?
b1010 #"
b1010 E
b1010 h
b1010 ]
0!
#35000
b11 I
b11 D
b11 i
b10 )
b10 2
b10 J
b10 R
b10 n
1!
#40000
b11110 A
b11110 f
b11110 %"
b11110 #
b11110 *
b11110 @
b11110 !"
b11110 O
b11110 W
b10100 Q
b10100 U
b10100 F
b10100 g
b10100 &
b10100 -
b10100 ?
b10100 #"
b10100 E
b10100 h
b10100 ]
b11 S
0!
#45000
b100 I
b100 D
b100 i
b11 )
b11 2
b11 J
b11 R
b11 n
1!
#50000
b101000 A
b101000 f
b101000 %"
b101000 #
b101000 *
b101000 @
b101000 !"
b101000 O
b101000 W
b11110 Q
b11110 U
b100 S
b11110 F
b11110 g
b11110 &
b11110 -
b11110 ?
b11110 #"
b11110 E
b11110 h
b11110 ]
0!
#55000
b101 I
b101 D
b101 i
b100 )
b100 2
b100 J
b100 R
b100 n
1!
#60000
b110010 A
b110010 f
b110010 %"
b110010 #
b110010 *
b110010 @
b110010 !"
b110010 O
b110010 W
b101000 Q
b101000 U
b101000 F
b101000 g
b101000 &
b101000 -
b101000 ?
b101000 #"
b101000 E
b101000 h
b101000 ]
b101 S
0!
#65000
b110 I
b110 D
b110 i
b101 )
b101 2
b101 J
b101 R
b101 n
1!
#70000
b111100 A
b111100 f
b111100 %"
b111100 #
b111100 *
b111100 @
b111100 !"
b111100 O
b111100 W
b110010 Q
b110010 U
b110 S
b110010 F
b110010 g
b110010 &
b110010 -
b110010 ?
b110010 #"
b110010 E
b110010 h
b110010 ]
0!
#75000
b111 I
b111 D
b111 i
b110 )
b110 2
b110 J
b110 R
b110 n
1!
#80000
b1000110 A
b1000110 f
b1000110 %"
b1000110 #
b1000110 *
b1000110 @
b1000110 !"
b1000110 O
b1000110 W
b111100 Q
b111100 U
b111100 F
b111100 g
b111100 &
b111100 -
b111100 ?
b111100 #"
b111100 E
b111100 h
b111100 ]
b111 S
0!
#85000
b1000011 A
b1000011 f
b1000011 %"
b1000011 #
b1000011 *
b1000011 @
b1000011 !"
b1000011 O
b1000011 W
b111 P
b111 V
b111 L
b111 K
b111 Z
b1000 I
b1001100111 Y
b1000 D
b1000 i
b1001001100111 %
b1001001100111 ,
b1001001100111 :
b1001001100111 C
b1001001100111 m
b111 )
b111 2
b111 J
b111 R
b111 n
1!
#90000
b1001010 A
b1001010 f
b1001010 %"
b1001010 #
b1001010 *
b1001010 @
b1001010 !"
b1001010 O
b1001010 W
b1000011 Q
b1000011 U
b1000 S
b1000011 F
b1000011 g
b1000011 &
b1000011 -
b1000011 ?
b1000011 #"
b1000011 E
b1000011 h
b1000011 ]
0!
#95000
0.
b1111111111111000 P
b1111111111111000 V
b1 A
b1 f
b1 %"
01
1'
b1111111111111000 L
b1 #
b1 *
b1 @
b1 !"
b1 O
b1 W
b1111111111111000 K
b1111111111111000 Z
b1001 I
b1001 Q
b1001 U
b10 5
b10 <
b10 >
b10 X
b0 F
b0 g
b111 H
b111 d
b1111111000 Y
b11 9
b1001 D
b1001 i
b11001111111000 %
b11001111111000 ,
b11001111111000 :
b11001111111000 C
b11001111111000 m
b1000 )
b1000 2
b1000 J
b1000 R
b1000 n
1!
#100000
b1001 S
b1000011 ""
b1000011 $
b1000011 +
b1000011 B
b1000011 $"
b1000011 p
0!
#105000
b1111111111110111 P
b1111111111110111 V
b1111111111110111 L
b1111111111110111 K
b1111111111110111 Z
b1 A
b1 f
bx $
bx +
bx B
bx $"
b1000011 %"
b1010 I
b1000011 ""
b1 #
b1 *
b1 @
b1 !"
b1 O
b1 W
1(
b1010 Q
b1010 U
b1111110111 Y
b1011 9
b1010 D
b1010 i
b1011001111110111 %
b1011001111110111 ,
b1011001111110111 :
b1011001111110111 C
b1011001111110111 m
b1001 )
b1001 2
b1001 J
b1001 R
b1001 n
1!
#110000
b1000011 $
b1000011 +
b1000011 B
b1000011 $"
b1000011 {
b1010 S
0!
#115000
b111000 P
b111000 V
0N
b0 L
b111000 K
b111000 Z
10
11
0'
b1000011 A
b1000011 f
b1000011 $
b1000011 +
b1000011 B
b1000011 $"
b1000011 %"
0/
b1011 I
b1000011 ""
b1000011 #
b1000011 *
b1000011 @
b1000011 !"
b1000011 O
b1000011 W
b10 M
b10 [
b0 &
b0 -
b0 ?
b0 #"
b0 E
b0 h
b0 G
b0 e
0(
b1011 Q
b1011 U
b0 H
b0 d
b10000111000 Y
b10 9
b1011 D
b1011 i
b10010000111000 %
b10010000111000 ,
b10010000111000 :
b10010000111000 C
b10010000111000 m
b1010 )
b1010 2
b1010 J
b1010 R
b1010 n
1!
#120000
b1000011 ^
b1011 S
0!
#125000
b1111111111110101 L
b1111111111110101 P
b1111111111110101 V
1N
b1111111111110101 K
b1111111111110101 Z
b1000011 A
b1000011 f
b1000011 $
b1000011 +
b1000011 B
b1000011 $"
b1000011 %"
b1100 I
b1000011 ""
b1 #
b1 *
b1 @
b1 !"
b1 O
b1 W
b11 M
b11 [
b101 G
b101 e
1(
b1100 Q
b1100 U
b111 H
b111 d
b11111110101 Y
b1010 9
b1100 D
b1100 i
b1010011111110101 %
b1010011111110101 ,
b1010011111110101 :
b1010011111110101 C
b1010011111110101 m
b1011 )
b1011 2
b1011 J
b1011 R
b1011 n
1!
#130000
b1100 S
b1000011 _
0!
#135000
1.
0N
b1100 P
b1100 V
b1100 A
b1100 f
00
b0 L
bx $
bx +
bx B
bx $"
b1100 %"
1/
b1100 K
b1100 Z
b1101 I
bx ""
b1100 #
b1100 *
b1100 @
b1100 !"
b1100 O
b1100 W
b0 M
b0 [
b0 G
b0 e
0(
b0 5
b0 <
b0 >
b0 X
b0 Q
b0 U
b0 H
b0 d
b101100 Y
b1 9
b1101 D
b1101 i
b1000000101100 %
b1000000101100 ,
b1000000101100 :
b1000000101100 C
b1000000101100 m
b1100 )
b1100 2
b1100 J
b1100 R
b1100 n
1!
#140000
b11000 A
b11000 f
b11000 %"
b11000 #
b11000 *
b11000 @
b11000 !"
b11000 O
b11000 W
b1100 Q
b1100 U
b1100 F
b1100 g
b1100 &
b1100 -
b1100 ?
b1100 #"
b1100 E
b1100 h
b1100 \
b1101 S
0!
#145000
b1110 I
b1110 D
b1110 i
b1101 )
b1101 2
b1101 J
b1101 R
b1101 n
1!
#150000
b100100 A
b100100 f
b100100 %"
b100100 #
b100100 *
b100100 @
b100100 !"
b100100 O
b100100 W
b11000 Q
b11000 U
b1110 S
b11000 F
b11000 g
b11000 &
b11000 -
b11000 ?
b11000 #"
b11000 E
b11000 h
b11000 \
0!
#155000
b1111 I
b1111 D
b1111 i
b1110 )
b1110 2
b1110 J
b1110 R
b1110 n
1!
#160000
b110000 A
b110000 f
b110000 %"
b110000 #
b110000 *
b110000 @
b110000 !"
b110000 O
b110000 W
b100100 Q
b100100 U
b100100 F
b100100 g
b100100 &
b100100 -
b100100 ?
b100100 #"
b100100 E
b100100 h
b100100 \
b1111 S
0!
#165000
b10000 I
b10000 D
b10000 i
b1111 )
b1111 2
b1111 J
b1111 R
b1111 n
1!
#170000
b111100 A
b111100 f
b111100 %"
b111100 #
b111100 *
b111100 @
b111100 !"
b111100 O
b111100 W
b110000 Q
b110000 U
b10000 S
b110000 F
b110000 g
b110000 &
b110000 -
b110000 ?
b110000 #"
b110000 E
b110000 h
b110000 \
0!
#175000
b1000011 $
b1000011 +
b1000011 B
b1000011 $"
b1000011 %"
b1000011 ""
b1000011 #
b1000011 *
b1000011 @
b1000011 !"
b1000011 O
b1000011 W
b1000011 A
b1000011 f
b10011 P
b10011 V
10
07
01
0/
b10011 K
b10011 Z
b10001 I
b100 M
b100 [
b1000011 &
b1000011 -
b1000011 ?
b1000011 #"
b1000011 E
b1000011 h
b11 G
b11 e
b1 5
b1 <
b1 >
b1 X
b10011 Y
b110 9
b10001 D
b10001 i
b110100000010011 %
b110100000010011 ,
b110100000010011 :
b110100000010011 C
b110100000010011 m
b10000 )
b10000 2
b10000 J
b10000 R
b10000 n
1!
#180000
b10001 S
0!
#185000
b110000 Q
b110000 U
b100100 A
b100100 f
bx $
bx +
bx B
bx $"
b100100 %"
1.
bx ""
b100100 #
b100100 *
b100100 @
b100100 !"
b100100 O
b100100 W
b1111111111110100 P
b1111111111110100 V
1/
00
11
b1111111111110100 K
b1111111111110100 Z
b10010 I
b0 M
b0 [
b110000 &
b110000 -
b110000 ?
b110000 #"
b110000 E
b110000 h
b0 G
b0 e
b0 5
b0 <
b0 >
b0 X
b110100 Y
b1 9
b10010 D
b10010 i
b1000000110100 %
b1000000110100 ,
b1000000110100 :
b1000000110100 C
b1000000110100 m
b10001 )
b10001 2
b10001 J
b10001 R
b10001 n
1!
